waypoint/__init__.py
waypoint/client/__init__.py
waypoint/client/base.py
waypoint/client/client.py
waypoint/data/__init__.py
waypoint/data/map_ids.py
waypoint/enum/__init__.py
waypoint/enum/game.py
waypoint/enum/game_variant.py
waypoint/models/__init__.py
waypoint/models/game_round.py
waypoint/models/stat.py
waypoint/utils/__init__.py
waypoint/utils/cookie_fetcher.py
waypoint/utils/round_mapper.py
waypoint-0.2.1.dist-info/LICENSE
waypoint-0.2.1.dist-info/METADATA
waypoint-0.2.1.dist-info/WHEEL
waypoint-0.2.1.dist-info/top_level.txt
waypoint-0.2.1.dist-info/RECORD
